netbox_storage/__init__.py
netbox_storage/api/serializers.py
netbox_storage/api/urls.py
netbox_storage/api/views.py
netbox_storage/apps.py
netbox_storage/filters/__init__.py
netbox_storage/filters/drive.py
netbox_storage/filters/filesystem.py
netbox_storage/forms/__init__.py
netbox_storage/forms/drive.py
netbox_storage/forms/filesystem.py
netbox_storage/migrations/0001_initial.py
netbox_storage/migrations/__init__.py
netbox_storage/models/__init__.py
netbox_storage/models/models.py
netbox_storage/navigation.py
netbox_storage/tables/__init__.py
netbox_storage/tables/drive.py
netbox_storage/tables/filesystem.py
netbox_storage/template_content.py
netbox_storage/templates/netbox_disk/disk/disk_box.html
netbox_storage/templates/netbox_disk/drive.html
netbox_storage/templates/netbox_disk/filesystem.html
netbox_storage/urls.py
netbox_storage/views/__init__.py
netbox_storage/views/drive.py
netbox_storage/views/filesystem.py
netbox_disk-0.0.7.6.5.66.dist-info/WHEEL
netbox_disk-0.0.7.6.5.66.dist-info/METADATA
netbox_disk-0.0.7.6.5.66.dist-info/RECORD
